dotpack/__init__.py
dotpack/ledbag.py
dotpack/ledpanel.py
dotpack/microblocks_client.py
dotpack/utils.py
dotpack/src/seguiemj.ttf
dotpack-0.3.6.dist-info/AUTHORS.rst
dotpack-0.3.6.dist-info/LICENSE
dotpack-0.3.6.dist-info/METADATA
dotpack-0.3.6.dist-info/WHEEL
dotpack-0.3.6.dist-info/top_level.txt
dotpack-0.3.6.dist-info/RECORD
