Metadata-Version: 2.1
Name: dotpack
Version: 0.3.6
Summary: Python Boilerplate contains all the boilerplate you need to create a Python package.
Home-page: https://github.com/longan-link/dotpack_pyclient
Author: Wenjie Wu
Author-email: wuwenjie718@gmail.com
License: GNU General Public License v3
Keywords: dotpack
Classifier: Development Status :: 2 - Pre-Alpha
Classifier: Intended Audience :: Developers
Classifier: License :: OSI Approved :: GNU General Public License v3 (GPLv3)
Classifier: Natural Language :: English
Classifier: Programming Language :: Python :: 3.6
Classifier: Programming Language :: Python :: 3.7
Classifier: Programming Language :: Python :: 3.8
License-File: LICENSE
License-File: AUTHORS.rst
Requires-Dist: bleak ==0.14.3
Requires-Dist: Pillow ==9.0.1
Requires-Dist: ipythonblocks ==1.9.0
Requires-Dist: loguru ==0.6.0
Requires-Dist: tqdm ==4.64.0
Requires-Dist: websocket-client ==1.3.2
